WebConf/__init__.py
WebConf/base_setting.py
WebConf/const.py
WebConf/error.py
WebConf/nginx.py
WebConf/public.py
WebConf/utils.py
WebConf/uwsgi.py
WebConf-0.0.2.dist-info/LICENSE
WebConf-0.0.2.dist-info/METADATA
WebConf-0.0.2.dist-info/WHEEL
WebConf-0.0.2.dist-info/top_level.txt
WebConf-0.0.2.dist-info/RECORD
