Metadata-Version: 2.1
Name: WebConf
Version: 0.0.2
Summary: Nginx conf is a Python package for configuring web services, which automatically configures uwsg and nginx files based on incoming parameters
Home-page: https://github.com/0716gzs/WebConf
Author: 0716gzs
Author-email: Jch_2154195820@163.com
License: Apache
Project-URL: Source, https://github.com/0716gzs/WebConf
Classifier: Development Status :: 5 - Production/Stable
Classifier: Environment :: Web Environment
Classifier: Intended Audience :: Developers
Classifier: License :: OSI Approved :: BSD License
Classifier: Operating System :: OS Independent
Classifier: Programming Language :: Python
Classifier: Programming Language :: Python :: 3
Classifier: Programming Language :: Python :: 3 :: Only
Classifier: Programming Language :: Python :: 3.6
Classifier: Programming Language :: Python :: 3.7
Classifier: Programming Language :: Python :: 3.8
Classifier: Topic :: Internet :: WWW/HTTP
Requires-Python: >=3.6
License-File: LICENSE
